{
  "movieList": [
    {
      "adult": false,
      "backdrop_path": "/d21yJNMG8C4E4rVJ4AqpTKJkIhQ.jpg",
      "genre_ids": [
        28,
        53,
        80,
        18
      ],
      "id": 37835,
      "original_language": "en",
      "original_title": "The Exterminator",
      "overview": "When a man's best friend is killed on the streets of New York, he transforms into a violent killer, turning New York into a war zone.",
      "popularity": 6.752,
      "poster_path": "/bOPjqqAMdxCO00ZVNLyq10tRFYr.jpg",
      "release_date": "1980-09-10",
      "title": "The Exterminator",
      "video": false,
      "vote_average": 5.7,
      "vote_count": 75
    },
    {
      "adult": false,
      "backdrop_path": "/7zydQ08HbdecIgl9EN0MgMWXlDL.jpg",
      "genre_ids": [
        28,
        35,
        37,
        10752
      ],
      "id": 48169,
      "original_language": "it",
      "original_title": "Il mercenario",
      "overview": "While a Mexican revolutionary lies low as a U.S. rodeo clown, the cynical Polish mercenary who tutored the idealistic peasant tells how he and a dedicated female radical fought for the soul of the guerrilla general Paco, as Mexicans threw off repressive government and all-powerful landowners in the 1910s. Tracked by the vengeful Curly, Paco liberates villages, but is tempted by social banditry's treasures, which Kowalski revels in.",
      "popularity": 6.702,
      "poster_path": "/mY8jDhQzXwYDDmw9upLfUbv07WC.jpg",
      "release_date": "1968-08-28",
      "title": "The Mercenary",
      "video": false,
      "vote_average": 7,
      "vote_count": 78
    },
    {
      "adult": false,
      "backdrop_path": "/iIVIHM5r6yk2mh318kCqk1RZ5tk.jpg",
      "genre_ids": [
        28,
        12,
        36,
        37
      ],
      "id": 37593,
      "original_language": "en",
      "original_title": "Lone Star",
      "overview": "Rip-roaring big star, big budget semi-historical story about cattle baron Devereaux Burke, who is enlisted by an aging Andrew Jackson to dissuade Sam Houston from establishing Texas as a republic. Burke must fight state senator Thomas Craden, in the process winning the heart of Craden's newspaper-editor girlfriend Martha Ronda.",
      "popularity": 2.426,
      "poster_path": "/8LukAkd59a3Fs5AehAmRP0DrApo.jpg",
      "release_date": "1952-10-24",
      "title": "Lone Star",
      "video": false,
      "vote_average": 5.5,
      "vote_count": 10
    }
  ]
}